cerebras/cloud/__init__.py
cerebras/cloud/sdk/__init__.py
cerebras/cloud/sdk/_base_client.py
cerebras/cloud/sdk/_client.py
cerebras/cloud/sdk/_compat.py
cerebras/cloud/sdk/_constants.py
cerebras/cloud/sdk/_exceptions.py
cerebras/cloud/sdk/_files.py
cerebras/cloud/sdk/_models.py
cerebras/cloud/sdk/_qs.py
cerebras/cloud/sdk/_resource.py
cerebras/cloud/sdk/_response.py
cerebras/cloud/sdk/_streaming.py
cerebras/cloud/sdk/_types.py
cerebras/cloud/sdk/_version.py
cerebras/cloud/sdk/py.typed
cerebras/cloud/sdk/_utils/__init__.py
cerebras/cloud/sdk/_utils/_compat.py
cerebras/cloud/sdk/_utils/_datetime_parse.py
cerebras/cloud/sdk/_utils/_logs.py
cerebras/cloud/sdk/_utils/_proxy.py
cerebras/cloud/sdk/_utils/_reflection.py
cerebras/cloud/sdk/_utils/_resources_proxy.py
cerebras/cloud/sdk/_utils/_streams.py
cerebras/cloud/sdk/_utils/_sync.py
cerebras/cloud/sdk/_utils/_transform.py
cerebras/cloud/sdk/_utils/_typing.py
cerebras/cloud/sdk/_utils/_utils.py
cerebras/cloud/sdk/lib/.keep
cerebras/cloud/sdk/resources/__init__.py
cerebras/cloud/sdk/resources/completions.py
cerebras/cloud/sdk/resources/models.py
cerebras/cloud/sdk/resources/chat/__init__.py
cerebras/cloud/sdk/resources/chat/chat.py
cerebras/cloud/sdk/resources/chat/completions.py
cerebras/cloud/sdk/types/__init__.py
cerebras/cloud/sdk/types/completion.py
cerebras/cloud/sdk/types/completion_create_params.py
cerebras/cloud/sdk/types/model_list_response.py
cerebras/cloud/sdk/types/model_retrieve_response.py
cerebras/cloud/sdk/types/chat/__init__.py
cerebras/cloud/sdk/types/chat/chat_completion.py
cerebras/cloud/sdk/types/chat/completion_create_params.py
cerebras_cloud_sdk-1.64.1.dist-info/METADATA
cerebras_cloud_sdk-1.64.1.dist-info/WHEEL
cerebras_cloud_sdk-1.64.1.dist-info/licenses/LICENSE
cerebras_cloud_sdk-1.64.1.dist-info/RECORD
